UNET_MDLE_CASE/XY.py
UNET_MDLE_CASE/__init__.py
UNET_MDLE_CASE/arc_unet.py
UNET_MDLE_CASE/gen_video.py
UNET_MDLE_CASE/pipeline.py
UNET_MDLE_CASE/plot_epochs.py
UNET_MDLE_CASE/pullcsv.py
UNET_MDLE_CASE/resizedim.py
UNET_MDLE_CASE/test_iou.py
UNET_MDLE_CASE/train.py
UNET_MDLE_CASE-0.2.dist-info/METADATA
UNET_MDLE_CASE-0.2.dist-info/WHEEL
UNET_MDLE_CASE-0.2.dist-info/top_level.txt
UNET_MDLE_CASE-0.2.dist-info/RECORD
